{
  "title": "Kai",
  "rules": [
    {
      "description": "Caps lock to hyper and escape",
      "manipulators": [
        {
          "type": "basic",
          "from": { "key_code": "caps_lock" },
          "to": [{ "key_code": "left_shift", "modifiers": ["left_command", "left_control", "left_option"], "lazy": true }],
          "to_if_alone": [{ "key_code": "escape" }],
          "parameters": { "basic.to_if_alone_timeout_milliseconds": 500 }
        }
      ]
    },
    {
      "description": "Disable macOS system diagnostic shortcuts to -=",
      "manipulators": [
        { "type": "basic", "from": { "key_code": "comma", "modifiers": { "mandatory": ["command", "control", "option", "shift"] } }, "to": [{ "key_code": "vk_none" }] },
        { "type": "basic", "from": { "key_code": "period", "modifiers": { "mandatory": ["command", "control", "option", "shift"] } }, "to": [{ "key_code": "vk_none" }] }
      ]
    },
    {
      "description": "App switcher hl to ←→",
      "manipulators": [
        {
          "type": "basic",
          "from": { "key_code": "h", "modifiers": { "mandatory": ["command"] } },
          "to": [{ "key_code": "left_arrow", "modifiers": ["command"] }],
          "conditions": [{ "type": "variable_if", "name": "app_switching", "value": 1 }]
        },
        {
          "type": "basic",
          "from": { "key_code": "l", "modifiers": { "mandatory": ["command"] } },
          "to": [{ "key_code": "right_arrow", "modifiers": ["command"] }],
          "conditions": [{ "type": "variable_if", "name": "app_switching", "value": 1 }]
        },
        { "type": "basic", "from": { "key_code": "tab", "modifiers": { "mandatory": ["command"] } }, "to": [{ "set_variable": { "name": "app_switching", "value": 1 } }, { "key_code": "tab", "modifiers": ["command"] }] },
        { "type": "basic", "from": { "key_code": "left_command" }, "to": [{ "set_variable": { "name": "app_switching", "value": 1, "key_up_value": 0 } }, { "key_code": "left_command" }] }
      ]
    },
    {
      "description": "Layer: right cmd",
      "manipulators": [
        // hyper + space
        {
          "type": "basic",
          "from": { "key_code": "right_command" },
          "to": [{ "key_code": "right_command" }],
          "to_if_alone": { "key_code": "spacebar", "modifiers": ["left_shift", "left_command", "left_option", "left_control"] },
          "parameters": { "basic.to_if_alone_timeout_milliseconds": 500 }
        },

        // ()
        { "type": "basic", "from": { "key_code": "e", "modifiers": { "mandatory": ["right_command"] } }, "to": [{ "key_code": "9", "modifiers": ["left_shift"] }] },
        { "type": "basic", "from": { "key_code": "r", "modifiers": { "mandatory": ["right_command"] } }, "to": [{ "key_code": "0", "modifiers": ["left_shift"] }] },
        // []
        { "type": "basic", "from": { "key_code": "d", "modifiers": { "mandatory": ["right_command"] } }, "to": [{ "key_code": "open_bracket" }] },
        { "type": "basic", "from": { "key_code": "f", "modifiers": { "mandatory": ["right_command"] } }, "to": [{ "key_code": "close_bracket" }] },
        // {}
        { "type": "basic", "from": { "key_code": "c", "modifiers": { "mandatory": ["right_command"] } }, "to": [{ "key_code": "open_bracket", "modifiers": ["left_shift"] }] },
        { "type": "basic", "from": { "key_code": "v", "modifiers": { "mandatory": ["right_command"] } }, "to": [{ "key_code": "close_bracket", "modifiers": ["left_shift"] }] },
        // _+
        { "type": "basic", "from": { "key_code": "q", "modifiers": { "mandatory": ["right_command"] } }, "to": [{ "key_code": "hyphen", "modifiers": ["left_shift"] }] },
        { "type": "basic", "from": { "key_code": "w", "modifiers": { "mandatory": ["right_command"] } }, "to": [{ "key_code": "equal_sign", "modifiers": ["left_shift"] }] },
        // -=
        { "type": "basic", "from": { "key_code": "a", "modifiers": { "mandatory": ["right_command"] } }, "to": [{ "key_code": "hyphen" }] },
        { "type": "basic", "from": { "key_code": "s", "modifiers": { "mandatory": ["right_command"] } }, "to": [{ "key_code": "equal_sign" }] },

        // VSCode, Cursor: copy relative path of active file
        {
          "type": "basic",
          "from": { "key_code": "c", "modifiers": { "mandatory": ["right_command"] } },
          "to": [
            { "key_code": "r", "modifiers": ["left_command"] },
            { "key_code": "c", "modifiers": ["left_command", "left_option", "left_shift"] }
          ],
          "conditions": [{ "type": "frontmost_application_if", "bundle_identifiers": ["com.microsoft.VSCode", "com.todesktop.230313mzl4w4u92"] }]
        }
      ]
    },
    {
      "description": "Layer: right opt",
      "manipulators": [
        // cmd + shift + []
        { "type": "basic", "from": { "key_code": "left_arrow", "modifiers": { "mandatory": ["right_option"] } }, "to": { "key_code": "open_bracket", "modifiers": ["left_shift", "left_command"] } },
        { "type": "basic", "from": { "key_code": "right_arrow", "modifiers": { "mandatory": ["right_option"] } }, "to": { "key_code": "close_bracket", "modifiers": ["left_shift", "left_command"] } },
        { "type": "basic", "from": { "key_code": "q", "modifiers": { "mandatory": ["right_option"] } }, "to": { "key_code": "q", "modifiers": ["left_control", "left_command"] } }
      ]
    }
  ]
}
